LICENSE
MANIFEST.in
README.rst
setup.cfg
setup.py
django_simple_pages.egg-info/PKG-INFO
django_simple_pages.egg-info/SOURCES.txt
django_simple_pages.egg-info/dependency_links.txt
django_simple_pages.egg-info/not-zip-safe
django_simple_pages.egg-info/top_level.txt
simple_pages/__init__.py
simple_pages/apps.py
simple_pages/middleware.py
simple_pages/run_tests.py
simple_pages/sitemap.py
simple_pages/widgets.py
simple_pages/admin/__init__.py
simple_pages/admin/page.py
simple_pages/migrations/0001_initial.py
simple_pages/migrations/0002_auto_20180825_2056.py
simple_pages/migrations/0003_auto_20180917_0943.py
simple_pages/migrations/__init__.py
simple_pages/models/__init__.py
simple_pages/models/page.py
simple_pages/static/simple_pages/vendor/codemirror/lib/codemirror.css
simple_pages/static/simple_pages/vendor/codemirror/lib/codemirror.js
simple_pages/static/simple_pages/vendor/codemirror/mode/css.js
simple_pages/static/simple_pages/vendor/codemirror/mode/htmlmixed.js
simple_pages/static/simple_pages/vendor/codemirror/mode/javascript.js
simple_pages/static/simple_pages/vendor/codemirror/mode/python.js
simple_pages/static/simple_pages/vendor/codemirror/mode/xml.js
simple_pages/templates/simple_pages/base.html
simple_pages/templates/simple_pages/default.html
simple_pages/templates/simple_pages/fade.html
simple_pages/templates/simple_pages/raw.html
simple_pages/views/__init__.py
simple_pages/views/page.py